README.rst
setup.py
countries/__init__.py
countries/models.py
countries.egg-info/PKG-INFO
countries.egg-info/SOURCES.txt
countries.egg-info/dependency_links.txt
countries.egg-info/requires.txt
countries.egg-info/top_level.txt
countries/fixtures/STATUS.txt
countries/fixtures/initial_data.json
countries/locale/de/LC_MESSAGES/django.mo
countries/locale/de/LC_MESSAGES/django.po
countries/management/__init__.py
countries/management/commands/__init__.py
countries/management/commands/country_export_gettext.py
countries/migrations/0001_initial.py
countries/migrations/0002_cleanup.py
countries/migrations/__init__.py